private_tools/__init__.py
private_tools/test.py
private_tools/my_tools_test_dir/cat_tool/__init__.py
private_tools/my_tools_test_dir/cat_tool/test.py
private_tools-0.0.0.dist-info/METADATA
private_tools-0.0.0.dist-info/WHEEL
private_tools-0.0.0.dist-info/top_level.txt
private_tools-0.0.0.dist-info/RECORD
